<?xml version="1.0" encoding="UTF-8"?>
<!DOCTYPE suite SYSTEM "http://testng.org/testng-1.0.dtd">
<suite name="中国地质大学在线学习平台" parallel="tests" preserve-order="true" thread-count="1">
<listeners>     
	<listener class-name="com.kkb.test.util.reporter.HTMLReporter" />
		<listener class-name="com.kkb.test.util.reporter.JUnitXMLReporter" />
	
	<listener class-name="com.kkb.test.util.reporter.TestngListener" />
</listeners>

	   	    	<parameter name="baseUrl" value="http://zgdzdx.gaoxiaobang.com/"/>
	   	    	<parameter name="loginName" value="13379209092"/>
	   	    	<parameter name="password" value="123456"/>

	   	   	   	   <test name="微信与口碑营销">
	    	<parameter name="courseName" value="微信与口碑营销"/>
	   		 <classes><class name="com.kkb.test.steps.pc.gxb.CoursePlayStep"/></classes>
	   </test>
	   	   	   	   	   <test name="数字化营销入门">
	    	<parameter name="courseName" value="数字化营销入门"/>
	   		 <classes><class name="com.kkb.test.steps.pc.gxb.CoursePlayStep"/></classes>
	   </test>
	   	   	   	   	   <test name="互联网营销全攻略">
	    	<parameter name="courseName" value="互联网营销全攻略"/>
	   		 <classes><class name="com.kkb.test.steps.pc.gxb.CoursePlayStep"/></classes>
	   </test>
	   	   	   	   	   <test name="信息安全意识与网络安全">
	    	<parameter name="courseName" value="信息安全意识与网络安全"/>
	   		 <classes><class name="com.kkb.test.steps.pc.gxb.CoursePlayStep"/></classes>
	   </test>
	   	   	   	   	   	   <test name="互联网金融零突破">
	    	<parameter name="courseName" value="互联网金融零突破"/>
	   		 <classes><class name="com.kkb.test.steps.pc.gxb.CoursePlayStep"/></classes>
	   </test>
	   	   	   	   	   	   <test name="从零起步学软文营销">
	    	<parameter name="courseName" value="从零起步学软文营销"/>
	   		 <classes><class name="com.kkb.test.steps.pc.gxb.CoursePlayStep"/></classes>
	   </test>
	   	   	   	   	   	   <test name="大数据营销与创新">
	    	<parameter name="courseName" value="大数据营销与创新"/>
	   		 <classes><class name="com.kkb.test.steps.pc.gxb.CoursePlayStep"/></classes>
	   </test>
	   	   	   	   	   	   	   <test name="留学第一课">
	    	<parameter name="courseName" value="留学第一课"/>
	   		 <classes><class name="com.kkb.test.steps.pc.gxb.CoursePlayStep"/></classes>
	   </test>
	   	   	   	   	   	   	   <test name="实用摄影基础教程">
	    	<parameter name="courseName" value="实用摄影基础教程"/>
	   		 <classes><class name="com.kkb.test.steps.pc.gxb.CoursePlayStep"/></classes>
	   </test>
	   	   	   	   	   	   	   <test name="网络风险评估">
	    	<parameter name="courseName" value="网络风险评估"/>
	   		 <classes><class name="com.kkb.test.steps.pc.gxb.CoursePlayStep"/></classes>
	   </test>
</suite>
