<?xml version="1.0" encoding="UTF-8"?>
<!DOCTYPE suite SYSTEM "http://testng.org/testng-1.0.dtd">


<!-- 修改学校名称 -->
<suite name="【奥美 · 云教育1-10】视频播放" parallel="tests" preserve-order="true"
	thread-count="1">
	<listeners>
		<listener class-name="com.kkb.test.util.reporter.HTMLReporter" />
		<listener class-name="com.kkb.test.util.reporter.JUnitXMLReporter" />
		<listener class-name="com.kkb.test.util.reporter.TestngListener" />
	</listeners>
	
	
	<!-- 修改下面三处，依次为学校首页，用户名 密码 -->
	<parameter name="baseUrl" value="http://acmeway.gaoxiaobang.com/" />
	<parameter name="loginName" value="gxb0000" />
	<parameter name="password" value="123456" />
	
	<!--配置课程-->
	
	
	<!--<test name="OpenStack云平台实践【精品课】">
		<parameter name="courseName" value="OpenStack云平台实践【精品课】" />
		<classes>
			<class name="com.kkb.test.steps.pc.gxb.CoursePlayStep" />
		</classes>
	</test>
	
	<test name="R语言建模与预测【精品课】">
		<parameter name="courseName" value="R语言建模与预测【精品课】" />
		<classes>
			<class name="com.kkb.test.steps.pc.gxb.CoursePlayStep" />
		</classes>
	</test>
	
	<test name="数据学的工具箱【精品课】">
		<parameter name="courseName" value="数据学的工具箱【精品课】" />
		<classes>
			<class name="com.kkb.test.steps.pc.gxb.CoursePlayStep" />
		</classes>
	</test>
	
	<test name="Spark集群环境部署与应用实践【精品课】">
		<parameter name="courseName" value="Spark集群环境部署与应用实践【精品课】" />
		<classes>
			<class name="com.kkb.test.steps.pc.gxb.CoursePlayStep" />
		</classes>
	</test>
	
	<test name="数据挖掘技术【精品课】">
		<parameter name="courseName" value="数据挖掘技术【精品课】" />
		<classes>
			<class name="com.kkb.test.steps.pc.gxb.CoursePlayStep" />
		</classes>
	</test>
	
	<test name="Android 平台移动云计算开发【精品课】">
		<parameter name="courseName" value="Android 平台移动云计算开发【精品课】" />
		<classes>
			<class name="com.kkb.test.steps.pc.gxb.CoursePlayStep" />
		</classes>
	</test>
	
	<test name="R语言编程技术【精品课】">
		<parameter name="courseName" value="R语言编程技术【精品课】" />
		<classes>
			<class name="com.kkb.test.steps.pc.gxb.CoursePlayStep" />
		</classes>
	</test>
		
	<test name="大数据概论【精品课】">
		<parameter name="courseName" value="大数据概论【精品课】" />
		<classes>
			<class name="com.kkb.test.steps.pc.gxb.CoursePlayStep" />
		</classes>
	</test>
	<test name="搜索引擎优化技术【精品课】">
		<parameter name="courseName" value="搜索引擎优化技术【精品课】" />
		<classes>
			<class name="com.kkb.test.steps.pc.gxb.CoursePlayStep" />
		</classes>
	</test>
	
	<test name="百度凤巢沙盒系统实习【精品课】">
		<parameter name="courseName" value="百度凤巢沙盒系统实习【精品课】" />
		<classes>
			<class name="com.kkb.test.steps.pc.gxb.CoursePlayStep" />
		</classes>
	</test>
	
	<test name="百度凤巢沙盒系统营销实践【精品课】">
		<parameter name="courseName" value="百度凤巢沙盒系统营销实践【精品课】" />
		<classes>
			<class name="com.kkb.test.steps.pc.gxb.CoursePlayStep" />
		</classes>
	</test>
	
	<test name="数据结构【精品课】">
		<parameter name="courseName" value="数据结构【精品课】" />
		<classes>
			<class name="com.kkb.test.steps.pc.gxb.CoursePlayStep" />
		</classes>
	</test>
	
	<test name="编程算法【精品课】">
		<parameter name="courseName" value="编程算法【精品课】" />
		<classes>
			<class name="com.kkb.test.steps.pc.gxb.CoursePlayStep" />
		</classes>
	</test>
	
	<test name="MySQL数据库高级技术【精品课】">
		<parameter name="courseName" value="MySQL数据库高级技术【精品课】" />
		<classes>
			<class name="com.kkb.test.steps.pc.gxb.CoursePlayStep" />
		</classes>
	</test>
	
	<test name="ThinkPHP框架技术【精品课】">
		<parameter name="courseName" value="ThinkPHP框架技术【精品课】" />
		<classes>
			<class name="com.kkb.test.steps.pc.gxb.CoursePlayStep" />
		</classes>
	</test>	
		
	<test name="PHP语言程序设计【精品课】">
		<parameter name="courseName" value="PHP语言程序设计【精品课】" />
		<classes>
			<class name="com.kkb.test.steps.pc.gxb.CoursePlayStep" />
		</classes>
	</test>

	<test name="CompTIA Cloud Essentials">
		<parameter name="courseName" value="CompTIA Cloud Essentials" />
		<classes>
			<class name="com.kkb.test.steps.pc.gxb.CoursePlayStep" />
		</classes>
	</test>
	
	<test name="数理统计【精品课】">
		<parameter name="courseName" value="数理统计【精品课】" />
		<classes>
			<class name="com.kkb.test.steps.pc.gxb.CoursePlayStep" />
		</classes>
	</test>
	
	<test name="静态网页技术【精品课】">
		<parameter name="courseName" value="静态网页技术【精品课】" />
		<classes>
			<class name="com.kkb.test.steps.pc.gxb.CoursePlayStep" />
		</classes>
	</test>
	
	<test name="搜索引擎营销【精品课】">
		<parameter name="courseName" value="搜索引擎营销【精品课】" />
		<classes>
			<class name="com.kkb.test.steps.pc.gxb.CoursePlayStep" />
		</classes>
	</test>
	
	<test name="互联网营销概论【精品课】">
		<parameter name="courseName" value="互联网营销概论【精品课】" />
		<classes>
			<class name="com.kkb.test.steps.pc.gxb.CoursePlayStep" />
		</classes>
	</test>
	
	<test name="社会化媒体营销【精品课】">
		<parameter name="courseName" value="社会化媒体营销【精品课】" />
		<classes>
			<class name="com.kkb.test.steps.pc.gxb.CoursePlayStep" />
		</classes>
	</test>
	
	<test name="Objective-C面向对象程序设计【精品课】">
		<parameter name="courseName" value="Objective-C面向对象程序设计【精品课】" />
		<classes>
			<class name="com.kkb.test.steps.pc.gxb.CoursePlayStep" />
		</classes>
	</test>
		
	<test name="MySQL数据库基础【精品课】">
		<parameter name="courseName" value="MySQL数据库基础【精品课】" />
		<classes>
			<class name="com.kkb.test.steps.pc.gxb.CoursePlayStep" />
		</classes>
	</test>
	
	<test name="高级编程语言【精品课】">
		<parameter name="courseName" value="高级编程语言【精品课】" />
		<classes>
			<class name="com.kkb.test.steps.pc.gxb.CoursePlayStep" />
		</classes>
	</test>

	<test name="演讲口才与公众表达">
		<parameter name="courseName" value="演讲口才与公众表达" />
		<classes>
			<class name="com.kkb.test.steps.pc.gxb.CoursePlayStep" />
		</classes>
	</test>
	
	<test name="形势与政策">
		<parameter name="courseName" value="形势与政策" />
		<classes>
			<class name="com.kkb.test.steps.pc.gxb.CoursePlayStep" />
		</classes>
	</test>
	<test name="国学素养">
		<parameter name="courseName" value="国学素养" />
		<classes>
			<class name="com.kkb.test.steps.pc.gxb.CoursePlayStep" />
		</classes>
	</test>
	
	<test name="安全教育">
		<parameter name="courseName" value="安全教育" />
		<classes>
			<class name="com.kkb.test.steps.pc.gxb.CoursePlayStep" />
		</classes>
	</test>-->
	<test name="奥美之路公司10年回顾">
		<parameter name="courseName" value="奥美之路公司10年回顾" />
		<classes>
			<class name="com.kkb.test.steps.pc.gxb.CoursePlayStep" />
		</classes>
	</test>
	<test name="体质与健康评价">
		<parameter name="courseName" value="体质与健康评价" />
		<classes>
			<class name="com.kkb.test.steps.pc.gxb.CoursePlayStep" />
		</classes>
	</test>
	<test name="客户项目系统穿越">
		<parameter name="courseName" value="客户项目系统穿越" />
		<classes>
			<class name="com.kkb.test.steps.pc.gxb.CoursePlayStep" />
		</classes>
	</test>
	<test name="营销产品系统穿越">
		<parameter name="courseName" value="营销产品系统穿越" />
		<classes>
			<class name="com.kkb.test.steps.pc.gxb.CoursePlayStep" />
		</classes>
	</test>
	<test name="销售中心2015年培训">
		<parameter name="courseName" value="销售中心2015年培训" />
		<classes>
			<class name="com.kkb.test.steps.pc.gxb.CoursePlayStep" />
		</classes>
	</test>
	<test name="行业和案例培训">
		<parameter name="courseName" value="行业和案例培训" />
		<classes>
			<class name="com.kkb.test.steps.pc.gxb.CoursePlayStep" />
		</classes>
	</test>
	<test name="运动营养与健康">
		<parameter name="courseName" value="运动营养与健康" />
		<classes>
			<class name="com.kkb.test.steps.pc.gxb.CoursePlayStep" />
		</classes>
	</test>
	<test name="德国肌肉力量测试及脊柱形态功能分析产品">
		<parameter name="courseName" value="德国肌肉力量测试及脊柱形态功能分析产品" />
		<classes>
			<class name="com.kkb.test.steps.pc.gxb.CoursePlayStep" />
		</classes>
	</test>
	<test name="心肺功能评价与健康促进">
		<parameter name="courseName" value="心肺功能评价与健康促进" />
		<classes>
			<class name="com.kkb.test.steps.pc.gxb.CoursePlayStep" />
		</classes>
	</test>
	<test name="运动与身体成分控制">
		<parameter name="courseName" value="运动与身体成分控制" />
		<classes>
			<class name="com.kkb.test.steps.pc.gxb.CoursePlayStep" />
		</classes>
	</test>
</suite>

